ai_orchestrator/__init__.py
ai_orchestrator/ollama_client.py
ai_orchestrator/.ipynb_checkpoints/ollama_client-checkpoint.py
ngs_ai_agent/__init__.py
ngs_ai_agent/cli.py
ngs_ai_agent/core.py
ngs_ai_agent/ai_orchestrator/__init__.py
ngs_ai_agent/ai_orchestrator/ollama_client.py
ngs_ai_agent/ai_orchestrator/.ipynb_checkpoints/ollama_client-checkpoint.py
ngs_ai_agent-1.1.1.dist-info/licenses/LICENSE
ngs_ai_agent-1.1.1.dist-info/METADATA
ngs_ai_agent-1.1.1.dist-info/WHEEL
ngs_ai_agent-1.1.1.dist-info/entry_points.txt
ngs_ai_agent-1.1.1.dist-info/top_level.txt
ngs_ai_agent-1.1.1.dist-info/RECORD
