Metadata-Version: 2.4
Name: ngs-ai-agent
Version: 1.1.1
Summary: AI-powered automated NGS analysis pipeline
Home-page: https://github.com/Wangyiquan95/ngs-ai-agent
Author: Wang, Yiquan
Author-email: contact@ngs-ai-agent.com
Project-URL: Bug Reports, https://github.com/Wangyiquan95/ngs-ai-agent/issues
Project-URL: Source, https://github.com/Wangyiquan95/ngs-ai-agent
Project-URL: Documentation, https://ngs-ai-agent.readthedocs.io/
Keywords: ngs,bioinformatics,ai,genomics,sequencing,pipeline
Classifier: Development Status :: 4 - Beta
Classifier: Intended Audience :: Science/Research
Classifier: Topic :: Scientific/Engineering :: Bio-Informatics
Classifier: License :: OSI Approved :: MIT License
Classifier: Programming Language :: Python :: 3
Classifier: Programming Language :: Python :: 3.8
Classifier: Programming Language :: Python :: 3.9
Classifier: Programming Language :: Python :: 3.10
Classifier: Programming Language :: Python :: 3.11
Classifier: Operating System :: OS Independent
Requires-Python: >=3.8
License-File: LICENSE
Provides-Extra: dev
Requires-Dist: pytest>=6.0; extra == "dev"
Requires-Dist: pytest-cov>=2.0; extra == "dev"
Requires-Dist: black>=21.0; extra == "dev"
Requires-Dist: flake8>=3.8; extra == "dev"
Requires-Dist: mypy>=0.800; extra == "dev"
Dynamic: author
Dynamic: author-email
Dynamic: classifier
Dynamic: description
Dynamic: description-content-type
Dynamic: home-page
Dynamic: keywords
Dynamic: license-file
Dynamic: project-url
Dynamic: provides-extra
Dynamic: requires-python
Dynamic: summary
